CLEMENT/Bunch.py
CLEMENT/CLEMENT.py
CLEMENT/EMhard.py
CLEMENT/Estep.py
CLEMENT/Mstep.py
CLEMENT/__init__.py
CLEMENT/clementrec.py
CLEMENT/comb.py
CLEMENT/datapreparation.py
CLEMENT/extract.py
CLEMENT/filetype.py
CLEMENT/graph.py
CLEMENT/isparent.py
CLEMENT/miscellaneous.py
CLEMENT/phylogeny.py
CLEMENT/result.py
CLEMENT/scoring.py
CLEMENT/visualizationeachstep.py
CLEMENT/visualizationpair.py
CLEMENT/visualizationpairsoft.py
CLEMENT/visualizationsingle.py
CLEMENT/visualizationsinglesoft.py
script/Bunch.py
script/CLEMENT.py
script/EMhard.py
script/Estep.py
script/Mstep.py
script/__init__.py
script/clementrec.py
script/comb.py
script/datapreparation.py
script/extract.py
script/filetype.py
script/graph.py
script/isparent.py
script/miscellaneous.py
script/phylogeny.py
script/result.py
script/scoring.py
script/visualizationeachstep.py
script/visualizationpair.py
script/visualizationpairsoft.py
script/visualizationsingle.py
script/visualizationsinglesoft.py
CLEMENTDNA-1.0.12.dist-info/METADATA
CLEMENTDNA-1.0.12.dist-info/WHEEL
CLEMENTDNA-1.0.12.dist-info/entry_points.txt
CLEMENTDNA-1.0.12.dist-info/top_level.txt
CLEMENTDNA-1.0.12.dist-info/RECORD
